spoolman/__init__.py
spoolman/exceptions.py
spoolman/models.py
spoolman/py.typed
spoolman/spoolman.py
spoolman-0.1.0.dist-info/LICENSE
spoolman-0.1.0.dist-info/METADATA
spoolman-0.1.0.dist-info/WHEEL
spoolman-0.1.0.dist-info/RECORD
